python_bitbay/__init__.py
python_bitbay/bitbay.py
python_bitbay/bitbay_ws.py
python_bitbay-0.1.2.dist-info/LICENSE
python_bitbay-0.1.2.dist-info/METADATA
python_bitbay-0.1.2.dist-info/WHEEL
python_bitbay-0.1.2.dist-info/top_level.txt
python_bitbay-0.1.2.dist-info/RECORD
