Metadata-Version: 2.1
Name: python-bitbay
Version: 0.1.2
Summary: Bitbay Exchange API python implementation for automated trading
Home-page: https://github.com/caiyundong/bitbay_api_python
Author: Cai Yundong
Author-email: yundong.cai@gmail.com
License: UNKNOWN
Platform: UNKNOWN
Classifier: Programming Language :: Python :: 3
Classifier: License :: OSI Approved :: MIT License
Classifier: Operating System :: OS Independent
